README.rst
setup.cfg
setup.py
Gladiator.egg-info/PKG-INFO
Gladiator.egg-info/SOURCES.txt
Gladiator.egg-info/dependency_links.txt
Gladiator.egg-info/not-zip-safe
Gladiator.egg-info/top_level.txt
gladiator/__init__.py
gladiator/commons.py
gladiator/core.py
gladiator/decorators.py
gladiator/utils.py
gladiator/validators.py