Metadata-Version: 1.1
Name: Gladiator
Version: 0.6.6
Summary: Gladiator is a Data Validation Framework for Python3
Home-page: https://github.com/laco/gladiator
Author: László Andrási
Author-email: mail@laszloandrasi.com
License: BSD
Download-URL: https://github.com/laco/gladiator/tarball/0.6.6
Platform: any
Classifier: Development Status :: 4 - Beta
Classifier: Environment :: Web Environment
Classifier: Intended Audience :: Developers
Classifier: License :: OSI Approved :: BSD License
Classifier: Operating System :: OS Independent
Classifier: Programming Language :: Python
Classifier: Programming Language :: Python :: 3
Classifier: Topic :: Internet :: WWW/HTTP :: Dynamic Content
Classifier: Topic :: Software Development :: Libraries :: Python Modules
